easy_coloc/__init__.py
easy_coloc/lib_easy_coloc.py
easy_coloc-1.2.dist-info/LICENSE
easy_coloc-1.2.dist-info/METADATA
easy_coloc-1.2.dist-info/WHEEL
easy_coloc-1.2.dist-info/top_level.txt
easy_coloc-1.2.dist-info/RECORD
