Metadata-Version: 2.1
Name: easy-coloc
Version: 1.2
Summary: A package for project model onto obs space 
Home-page: UNKNOWN
Author: Raphael Dussin
Author-email: raphael.dussin@gmail.com
License: GPLv3
Keywords: ocean modeling / observations
Platform: UNKNOWN
